trame_common/__init__.py
trame_common/assets/__init__.py
trame_common/assets/local.py
trame_common/assets/mimetypes.py
trame_common/assets/remote.py
trame_common/decorators/__init__.py
trame_common/decorators/hot_reload.py
trame_common/decorators/klass.py
trame_common/exec/__init__.py
trame_common/exec/asynchronous.py
trame_common/exec/throttle.py
trame_common/obj/__init__.py
trame_common/obj/app.py
trame_common/obj/component.py
trame_common/obj/singleton.py
trame_common/obj/widget.py
trame_common/utils/__init__.py
trame_common/utils/version.py
trame_common-1.1.0.dist-info/METADATA
trame_common-1.1.0.dist-info/WHEEL
trame_common-1.1.0.dist-info/licenses/LICENSE
trame_common-1.1.0.dist-info/RECORD
